src/mcp_tool_builder/__about__.py
src/mcp_tool_builder/__init__.py
src/mcp_tool_builder/cli.py
src/mcp_tool_builder/tool_builder_server.py
tools/get_bitcoin_price.py
tools/get_weather_forecast.py
tools/tools.json
orange1_mcp_tool_builder-0.1.0.dist-info/METADATA
orange1_mcp_tool_builder-0.1.0.dist-info/WHEEL
orange1_mcp_tool_builder-0.1.0.dist-info/entry_points.txt
orange1_mcp_tool_builder-0.1.0.dist-info/licenses/LICENSE
orange1_mcp_tool_builder-0.1.0.dist-info/RECORD
